ddtrace/__init__.py
ddtrace/_logger.py
ddtrace/_monkey.py
ddtrace/auto.py
ddtrace/constants.py
ddtrace/data_streams.py
ddtrace/py.typed
ddtrace/version.py
ddtrace/_trace/__init__.py
ddtrace/_trace/_inferred_proxy.py
ddtrace/_trace/_limits.py
ddtrace/_trace/_span_link.py
ddtrace/_trace/_span_pointer.py
ddtrace/_trace/apm_filter.py
ddtrace/_trace/context.py
ddtrace/_trace/filters.py
ddtrace/_trace/pin.py
ddtrace/_trace/product.py
ddtrace/_trace/provider.py
ddtrace/_trace/sampler.py
ddtrace/_trace/sampling_rule.py
ddtrace/_trace/span.py
ddtrace/_trace/telemetry.py
ddtrace/_trace/trace_handlers.py
ddtrace/_trace/tracer.py
ddtrace/_trace/types.py
ddtrace/_trace/utils.py
ddtrace/_trace/utils_valkey.py
ddtrace/_trace/processor/__init__.py
ddtrace/_trace/processor/resource_renaming.py
ddtrace/_trace/utils_botocore/__init__.py
ddtrace/_trace/utils_botocore/aws_payload_tagging.py
ddtrace/_trace/utils_botocore/span_tags.py
ddtrace/_trace/utils_botocore/span_pointers/__init__.py
ddtrace/_trace/utils_botocore/span_pointers/dynamodb.py
ddtrace/_trace/utils_botocore/span_pointers/s3.py
ddtrace/_trace/utils_botocore/span_pointers/telemetry.py
ddtrace/appsec/__init__.py
ddtrace/appsec/_asm_request_context.py
ddtrace/appsec/_capabilities.py
ddtrace/appsec/_common_module_patches.py
ddtrace/appsec/_constants.py
ddtrace/appsec/_deduplications.py
ddtrace/appsec/_handlers.py
ddtrace/appsec/_http_utils.py
ddtrace/appsec/_listeners.py
ddtrace/appsec/_metrics.py
ddtrace/appsec/_processor.py
ddtrace/appsec/_remoteconfiguration.py
ddtrace/appsec/_trace_utils.py
ddtrace/appsec/_utils.py
ddtrace/appsec/rules.json
ddtrace/appsec/track_user_sdk.py
ddtrace/appsec/_ai_guard/__init__.py
ddtrace/appsec/_ai_guard/_langchain.py
ddtrace/appsec/_ai_guard/_listener.py
ddtrace/appsec/_api_security/__init__.py
ddtrace/appsec/_api_security/api_manager.py
ddtrace/appsec/_ddwaf/__init__.py
ddtrace/appsec/_ddwaf/ddwaf_types.py
ddtrace/appsec/_ddwaf/waf.py
ddtrace/appsec/_ddwaf/waf_mock.py
ddtrace-4.3.1.dist-info/licenses/LICENSE
ddtrace-4.3.1.dist-info/licenses/LICENSE.Apache
ddtrace-4.3.1.dist-info/licenses/LICENSE.BSD3
ddtrace-4.3.1.dist-info/licenses/NOTICE
ddtrace-4.3.1.dist-info/METADATA
ddtrace-4.3.1.dist-info/WHEEL
ddtrace-4.3.1.dist-info/entry_points.txt
ddtrace-4.3.1.dist-info/top_level.txt
ddtrace-4.3.1.dist-info/RECORD
