Metadata-Version: 2.4
Name: ddtrace
Version: 4.3.1
Summary: Datadog APM client library
Author-email: "Datadog, Inc." <dev@datadoghq.com>
License: LICENSE.BSD3
Project-URL: Bug Tracker, https://github.com/DataDog/dd-trace-py/issues
Project-URL: Changelog, https://github.com/DataDog/dd-trace-py/releases
Project-URL: Documentation, https://ddtrace.readthedocs.io/en/stable/
Project-URL: Homepage, https://github.com/DataDog/dd-trace-py
Project-URL: Source Code, https://github.com/DataDog/dd-trace-py/
Classifier: Development Status :: 5 - Production/Stable
Classifier: Programming Language :: Python :: Implementation :: CPython
Classifier: Programming Language :: Python
Classifier: Programming Language :: Python :: 3 :: Only
Classifier: Programming Language :: Python :: 3.9
Classifier: Programming Language :: Python :: 3.10
Classifier: Programming Language :: Python :: 3.11
Classifier: Programming Language :: Python :: 3.12
Classifier: Programming Language :: Python :: 3.13
Classifier: Programming Language :: Python :: 3.14
Requires-Python: <3.15,>=3.9
License-File: LICENSE
License-File: LICENSE.Apache
License-File: LICENSE.BSD3
License-File: NOTICE
Requires-Dist: bytecode<1,>=0.17.0; python_version >= "3.14.0"
Requires-Dist: bytecode<1,>=0.16.0; python_version >= "3.13.0"
Requires-Dist: bytecode<1,>=0.15.1; python_version ~= "3.12.0"
Requires-Dist: bytecode<1,>=0.14.0; python_version ~= "3.11.0"
Requires-Dist: bytecode<1,>=0.13.0; python_version < "3.11"
Requires-Dist: envier~=0.6.1
Requires-Dist: opentelemetry-api<2,>=1
Requires-Dist: wrapt<3,>=1
Provides-Extra: opentracing
Requires-Dist: opentracing<3,>=2; extra == "opentracing"
Provides-Extra: opentelemetry
Requires-Dist: opentelemetry-exporter-otlp<2,>=1; extra == "opentelemetry"
Dynamic: license-file
